{
    "state": "COMPLETE",
    "gameResult": {
        "gameInstanceId": 999,
        "stakePence": 100,
        "isWin": false,
        "totalWinPence": 2800,
        "decimalOdds": 0.0,
        "integrationResultData": {
"bonusList": [
            {
                "riderNumber": "N",
                "riderName": "",
                "clipType": "NO WIN",
                "externalReference": "vid-mgp-sbdjjc2y9aijdv1"
            }
        ],
            "bonusWin": 2400,
            "bonusStake": 100,
            "stakes": [
                {
                    "type": "straight",
                    "cells": [
                        1
                    ],
                    "buttonId": 1,
                    "amountsPence": 100
                }
            ],
            "winNumber": 1
        }
    },
    "wagerNumber": 1097912,
    "startTime": "0001-01-01T00:00:00",
    "operationResult": 0,
    "upstream": {
        "txId": "1097912",
        "processedTxId": "5A3EPuXiPZ",
        "createdAt": "2025-06-09T07:26:11Z",
        "balance": 1000,
        "alreadyProcessed": false,
        "status": 0,
        "errDesc": null
    },
    "referenceGuid": "90665829-28d3-4028-86e8-bb80519928fe"
}